odoo/addons/quality_control_team/README.rst
odoo/addons/quality_control_team/__init__.py
odoo/addons/quality_control_team/__manifest__.py
odoo/addons/quality_control_team/data/quality_control_team_data.xml
odoo/addons/quality_control_team/i18n/de.po
odoo/addons/quality_control_team/i18n/pt.po
odoo/addons/quality_control_team/i18n/pt_BR.po
odoo/addons/quality_control_team/i18n/quality_control_team.pot
odoo/addons/quality_control_team/models/__init__.py
odoo/addons/quality_control_team/models/qc_team.py
odoo/addons/quality_control_team/models/res_partner.py
odoo/addons/quality_control_team/models/res_user.py
odoo/addons/quality_control_team/readme/CONFIGURE.rst
odoo/addons/quality_control_team/readme/CONTRIBUTORS.rst
odoo/addons/quality_control_team/readme/DESCRIPTION.rst
odoo/addons/quality_control_team/security/ir.model.access.csv
odoo/addons/quality_control_team/static/description/icon.png
odoo/addons/quality_control_team/static/description/icon.svg
odoo/addons/quality_control_team/static/description/index.html
odoo/addons/quality_control_team/tests/__init__.py
odoo/addons/quality_control_team/tests/test_quality_control_team.py
odoo/addons/quality_control_team/views/qc_team_dashboard.xml
odoo/addons/quality_control_team/views/qc_team_view.xml
odoo12_addon_quality_control_team-12.0.1.1.1.dist-info/METADATA
odoo12_addon_quality_control_team-12.0.1.1.1.dist-info/WHEEL
odoo12_addon_quality_control_team-12.0.1.1.1.dist-info/top_level.txt
odoo12_addon_quality_control_team-12.0.1.1.1.dist-info/RECORD
